rasgotransforms/__init__.py
rasgotransforms/dtypes.py
rasgotransforms/exceptions.py
rasgotransforms/main.py
rasgotransforms/version.py
rasgotransforms/macros/combine_groups.sql
rasgotransforms/macros/distinct_values.sql
rasgotransforms/macros/expression_metrics.sql
rasgotransforms/macros/filter.sql
rasgotransforms/macros/period_over_period.sql
rasgotransforms/macros/period_to_date.sql
rasgotransforms/macros/prior.sql
rasgotransforms/macros/rolling.sql
rasgotransforms/macros/secondary_calculation.sql
rasgotransforms/macros/bigquery/aggregate_metrics.sql
rasgotransforms/macros/bigquery/pivot.sql
rasgotransforms/macros/snowflake/aggregate_metrics.sql
rasgotransforms/macros/snowflake/pivot.sql
rasgotransforms/render/__init__.py
rasgotransforms/render/environment.py
rasgotransforms/render/infer_columns.py
rasgotransforms/render/transforms.py
rasgotransforms/snippets/agg.sql
rasgotransforms/snippets/agg_dict.sql
rasgotransforms/snippets/alias.sql
rasgotransforms/snippets/boolean.sql
rasgotransforms/snippets/calculated_column_list.sql
rasgotransforms/snippets/column.sql
rasgotransforms/snippets/column_agg_list.sql
rasgotransforms/snippets/column_list.sql
rasgotransforms/snippets/column_or_expression.sql
rasgotransforms/snippets/column_or_expression_list.sql
rasgotransforms/snippets/column_value.sql
rasgotransforms/snippets/column_value_list.sql
rasgotransforms/snippets/custom_option.sql
rasgotransforms/snippets/custom_option_list.sql
rasgotransforms/snippets/date.sql
rasgotransforms/snippets/date_part.sql
rasgotransforms/snippets/filter_list.sql
rasgotransforms/snippets/int.sql
rasgotransforms/snippets/join_type.sql
rasgotransforms/snippets/number.sql
rasgotransforms/snippets/number_list.sql
rasgotransforms/snippets/sort_dict.sql
rasgotransforms/snippets/sort_direction.sql
rasgotransforms/snippets/string.sql
rasgotransforms/snippets/string_list.sql
rasgotransforms/snippets/table.sql
rasgotransforms/snippets/table_list.sql
rasgotransforms/snippets/timestamp.sql
rasgotransforms-2.7.8.dist-info/METADATA
rasgotransforms-2.7.8.dist-info/WHEEL
rasgotransforms-2.7.8.dist-info/top_level.txt
rasgotransforms-2.7.8.dist-info/RECORD
