Metadata-Version: 2.1
Name: rasgotransforms
Version: 2.7.8
Summary: Open-source SQL transform templates provided by RasgoML.
Author: Rasgo Intelligence
Author-email: patrick@rasgoml.com
License: GNU Affero General Public License v3 or later (AGPLv3+)
Project-URL: Documentation, https://docs.rasgoml.com/rasgo-docs/transforms/overview
Project-URL: Source, https://github.com/rasgointelligence/RasgoTransforms
Project-URL: Rasgo, https://www.rasgoml.com/
Classifier: Development Status :: 3 - Alpha
Classifier: License :: OSI Approved :: GNU Affero General Public License v3 or later (AGPLv3+)
Classifier: Intended Audience :: Science/Research
Classifier: Intended Audience :: Developers
Classifier: Programming Language :: Python :: 3.7
Classifier: Programming Language :: Python :: 3.8
Classifier: Programming Language :: Python :: 3.9
Classifier: Programming Language :: Python :: 3.10
Classifier: Programming Language :: Python :: 3.11
Classifier: Topic :: Database
Classifier: Topic :: Scientific/Engineering :: Information Analysis
Classifier: Topic :: Software Development :: Code Generators
Requires-Dist: jinja2 >=2.0
Requires-Dist: pyyaml >=5.0
